<manifest alg="2" build="2015.0.0.309" opt="false" iceEnabled="true" iceMarkupVersion="2" exportTarget="other" domain="www.fen.com" resolutions="1x" timestamp="1446437767278">
  <folder name="css">
    <file name="site_global.css" crc="4090775803"/>
    <file name="master_a-master.css" crc="4096321838" ref="index"/>
    <file name="index.css" crc="445532147" ref="index"/>
    <file name="iefonts_index.css" crc="111371451" ref="index"/>
  </folder>
  <folder name="scripts">
    <file name="jquery-1.8.3.min.js" crc="4255413929" ref="phone>index:tablet>index:index"/>
    <file name="museutils.js" crc="183364071" ref="phone>index:tablet>index:index"/>
    <file name="pie.js" crc="3827607177" ref="phone>index"/>
    <file name="webpro.js" crc="3803554875" ref="phone>index:tablet>index:index"/>
    <file name="form_check.php" crc="277267350" ref="phone>index:tablet>index:index"/>
    <file name="form_throttle.php" crc="3908387251" ref="phone>index:tablet>index:index"/>
    <file name="form_process.php" crc="24249335" ref="phone>index:tablet>index:index"/>
    <file name="form-u1229.php" crc="35790778" ref="phone>index"/>
    <file name="jquery.watch.js" crc="71412426" ref="phone>index:tablet>index:index"/>
    <file name="museredirect.js" crc="40941066" ref="tablet>index:index"/>
    <file name="jquery.scrolleffects.js" crc="3860644955" ref="tablet>index:index"/>
    <file name="form-u1336.php" crc="361272591" ref="tablet>index"/>
    <file name="form-u886.php" crc="168998856" ref="index"/>
  </folder>
  <folder name="images">
    <file name="new one.gif" crc="3965659382" seo="true" ref="phone>index:tablet>index:index"/>
    <file name="u1204-4.png" crc="63640196" ref="phone>index"/>
    <file name="beach 1_2.jpg" crc="4289001105" ref="phone>index"/>
    <file name="u1206-grad.png" crc="4238805812" ref="phone>index"/>
    <file name="blank.gif" crc="4208392903" ref="phone>index:tablet>index:index"/>
    <file name="u1211.png" crc="155192465" ref="phone>index"/>
    <file name="u1211-r.png" crc="155192465" ref="phone>index"/>
    <file name="femi lag 1 copy.jpg" crc="4051423380" ref="phone>index"/>
    <file name="u1213-grad.png" crc="22489469" ref="phone>index"/>
    <file name="u1216-6.png" crc="289268153" ref="phone>index"/>
    <file name="u1217.png" crc="733762" ref="phone>index"/>
    <file name="u1217-r.png" crc="733762" ref="phone>index"/>
    <file name="beach 22.jpg" crc="3875056113" ref="phone>index"/>
    <file name="u1228-grad.png" crc="270092569" ref="phone>index"/>
    <file name="u1231-17.png" crc="3881842551" ref="phone>index"/>
    <file name="u1231-17-r.png" crc="80360787" ref="phone>index"/>
    <file name="u1231-17-m.png" crc="80360787" ref="phone>index"/>
    <file name="u1231-17-fs.png" crc="369176929" ref="phone>index"/>
    <file name="facebook.png" crc="4059342059" seo="true" ref="phone>index:tablet>index:index"/>
    <file name="twitter.png" crc="422856021" seo="true" ref="phone>index:tablet>index:index"/>
    <file name="google.png" crc="3955338726" seo="true" ref="phone>index:tablet>index:index"/>
    <file name="beach 1.jpg" crc="443951639" ref="tablet>index:index"/>
    <file name="u1320-grad.png" crc="3840545126" ref="tablet>index:index"/>
    <file name="u1399-5.png" crc="64904862" ref="tablet>index"/>
    <file name="pattern.jpg" crc="4213927747" ref="tablet>index:index"/>
    <file name="u1382.png" crc="295278632" ref="tablet>index"/>
    <file name="u1382-r.png" crc="295278632" ref="tablet>index"/>
    <file name="femi lag 1 copy2.jpg" crc="4051423380" seo="true" ref="tablet>index:index"/>
    <file name="u1402-grad.png" crc="464983018" ref="tablet>index:index"/>
    <file name="femi.jpg" crc="4091559994" ref="tablet>index:index"/>
    <file name="u1386-grad.png" crc="219068043" ref="tablet>index:index"/>
    <file name="u1323.png" crc="64734902" ref="tablet>index"/>
    <file name="u1323-r.png" crc="64734902" ref="tablet>index"/>
    <file name="u1324.png" crc="256119252" ref="tablet>index"/>
    <file name="u1324-r.png" crc="256119252" ref="tablet>index"/>
    <file name="u1326.png" crc="511369531" ref="tablet>index"/>
    <file name="u1326-r.png" crc="511369531" ref="tablet>index"/>
    <file name="u1327.png" crc="4225518816" ref="tablet>index"/>
    <file name="u1327-r.png" crc="4225518816" ref="tablet>index"/>
    <file name="u1329.png" crc="4098336219" ref="tablet>index"/>
    <file name="u1329-r.png" crc="4098336219" ref="tablet>index"/>
    <file name="u1331.png" crc="84223936" ref="tablet>index"/>
    <file name="u1331-r.png" crc="84223936" ref="tablet>index"/>
    <file name="beach 2.jpg" crc="364656223" ref="tablet>index:index"/>
    <file name="u1350-17.png" crc="3881842551" ref="tablet>index"/>
    <file name="u1350-17-r.png" crc="80360787" ref="tablet>index"/>
    <file name="u1350-17-m.png" crc="80360787" ref="tablet>index"/>
    <file name="u1350-17-fs.png" crc="369176929" ref="tablet>index"/>
    <file name="u1032-5.png" crc="64904862" ref="index"/>
    <file name="u936.png" crc="303195013" ref="index"/>
    <file name="u936-r.png" crc="303195013" ref="index"/>
    <file name="u852.png" crc="64734902" ref="index"/>
    <file name="u852-r.png" crc="64734902" ref="index"/>
    <file name="u853.png" crc="256119252" ref="index"/>
    <file name="u853-r.png" crc="256119252" ref="index"/>
    <file name="u858.png" crc="511369531" ref="index"/>
    <file name="u858-r.png" crc="511369531" ref="index"/>
    <file name="u859.png" crc="4225518816" ref="index"/>
    <file name="u859-r.png" crc="4225518816" ref="index"/>
    <file name="u865.png" crc="4098336219" ref="index"/>
    <file name="u865-r.png" crc="4098336219" ref="index"/>
    <file name="u871.png" crc="84223936" ref="index"/>
    <file name="u871-r.png" crc="84223936" ref="index"/>
    <file name="u887-17.png" crc="3881842551" ref="index"/>
    <file name="u887-17-r.png" crc="80360787" ref="index"/>
    <file name="u887-17-m.png" crc="80360787" ref="index"/>
    <file name="u887-17-fs.png" crc="369176929" ref="index"/>
  </folder>
  <folder name="tablet">
    <folder name="css">
      <file name="master_a-master.css" crc="218474826" ref="tablet>index"/>
      <file name="index.css" crc="131444420" ref="tablet>index"/>
      <file name="iefonts_index.css" crc="370040944" ref="tablet>index"/>
    </folder>
    <file name="index.html" crc="4212953923" seo="true" mt="1446437364837" redirect="true"/>
  </folder>
  <folder name="phone">
    <folder name="css">
      <file name="master_a-master.css" crc="4263883084" ref="phone>index"/>
      <file name="index.css" crc="128732005" ref="phone>index"/>
      <file name="iefonts_index.css" crc="80712561" ref="phone>index"/>
    </folder>
    <file name="index.html" crc="4169832669" seo="true" mt="1446435138358" redirect="true"/>
  </folder>
  <file name="index.html" crc="121872388" seo="true" mt="1446437342588" redirect="true"/>
</manifest>